binay_parajuli/__init__.py
binay_parajuli/main.py
binay_parajuli-0.1.1.dist-info/LICENSE.txt
binay_parajuli-0.1.1.dist-info/METADATA
binay_parajuli-0.1.1.dist-info/WHEEL
binay_parajuli-0.1.1.dist-info/entry_points.txt
binay_parajuli-0.1.1.dist-info/top_level.txt
binay_parajuli-0.1.1.dist-info/RECORD
