Metadata-Version: 2.1
Name: binay_parajuli
Version: 0.1.1
Author: Binay Raj Parajuli
Author-email: binayaparajuli17@gmail.com
License-File: LICENSE.txt
